setup.py
ashwin_indian_states_25/__init__.py
ashwin_indian_states_25/asgi.py
ashwin_indian_states_25/settings.py
ashwin_indian_states_25/urls.py
ashwin_indian_states_25/wsgi.py
ashwin_indian_states_25.egg-info/PKG-INFO
ashwin_indian_states_25.egg-info/SOURCES.txt
ashwin_indian_states_25.egg-info/dependency_links.txt
ashwin_indian_states_25.egg-info/requires.txt
ashwin_indian_states_25.egg-info/top_level.txt
kst1/__init__.py
kst1/admin.py
kst1/apps.py
kst1/models.py
kst1/tests.py
kst1/views.py
kst1/migrations/__init__.py